fastapi_inroute/__init__.py
fastapi_inroute/client.py
fastapi_inroute/config.py
fastapi_inroute/manager.py
fastapi_inroute/middleware.py
fastapi_inroute/processor.py
fastapi_inroute/server.py
fastapi_inroute/setup.py
fastapi_inroute-0.1.1.dist-info/WHEEL
fastapi_inroute-0.1.1.dist-info/entry_points.txt
fastapi_inroute-0.1.1.dist-info/METADATA
fastapi_inroute-0.1.1.dist-info/RECORD
