Metadata-Version: 2.3
Name: fastapi-inroute
Version: 0.1.1
Summary: WebSocket-based request forwarding for FastAPI applications - develop and debug webhooks locally
Keywords: fastapi,webhook,websocket,development,debugging,forwarding
Author: puneet
Author-email: puneet <puneet@ibm.com>
License: MIT
Classifier: Development Status :: 4 - Beta
Classifier: Intended Audience :: Developers
Classifier: License :: OSI Approved :: MIT License
Classifier: Programming Language :: Python :: 3
Classifier: Programming Language :: Python :: 3.11
Classifier: Programming Language :: Python :: 3.12
Classifier: Framework :: FastAPI
Classifier: Topic :: Software Development :: Libraries :: Python Modules
Classifier: Topic :: Internet :: WWW/HTTP :: HTTP Servers
Requires-Dist: fastapi[standard]>=0.128.0
Requires-Dist: websockets>=16.0
Requires-Python: >=3.11
Project-URL: Documentation, https://github.com/PuneetUdhayan/fastapi-inroute#readme
Project-URL: Homepage, https://github.com/PuneetUdhayan/fastapi-inroute
Project-URL: Issues, https://github.com/PuneetUdhayan/fastapi-inroute/issues
Project-URL: Repository, https://github.com/PuneetUdhayan/fastapi-inroute
